{"map_file": "map_1", "score": 4, "date": "20240624170607", "definitions": [{"definition_type": "3", "i": 0, "j": 0, "word": "soupconneux", "definition": "soupconneux"}, {"definition_type": "6", "i": 0, "j": 0, "word": "goyavier", "definition": "goyavier"}, {"definition_type": "3", "i": 0, "j": 6, "word": "artisan", "definition": "artisan"}, {"definition_type": "1", "i": 2, "j": 0, "word": "uniment", "definition": "uniment"}, {"definition_type": "2", "i": 3, "j": 5, "word": "melissa", "definition": "melissa"}, {"definition_type": "6", "i": 6, "j": 0, "word": "entrait", "definition": "entrait"}, {"definition_type": "1", "i": 8, "j": 0, "word": "egrisee", "definition": "egrisee"}, {"definition_type": "6", "i": 4, "j": 0, "word": "mortne", "definition": "mortne"}, {"definition_type": "2", "i": 4, "j": 3, "word": "terril", "definition": "terril"}, {"definition_type": "6", "i": 2, "j": 0, "word": "appli", "definition": "appli"}, {"definition_type": "2", "i": 5, "j": 6, "word": "iteur", "definition": "iteur"}, {"definition_type": "1", "i": 9, "j": 2, "word": "issue", "definition": "issue"}, {"definition_type": "3", "i": 0, "j": 2, "word": "rail", "definition": "rail"}, {"definition_type": "1", "i": 4, "j": 3, "word": "amas", "definition": "amas"}, {"definition_type": "3", "i": 0, "j": 4, "word": "cie", "definition": "cie"}, {"definition_type": "1", "i": 6, "j": 0, "word": "nue", "definition": "nue"}, {"definition_type": "1", "i": 6, "j": 4, "word": "lin", "definition": "lin"}, {"definition_type": "2", "i": 6, "j": 4, "word": "ais", "definition": "ais"}, {"definition_type": "2", "i": 7, "j": 7, "word": "een", "definition": "een"}, {"definition_type": "1", "i": 10, "j": 0, "word": "xml", "definition": "xml"}, {"definition_type": "1", "i": 10, "j": 4, "word": "arn", "definition": "arn"}, {"definition_type": "1", "i": 3, "j": 5, "word": "qi", "definition": "qi"}, {"definition_type": "1", "i": 4, "j": 0, "word": "ch", "definition": "ch"}, {"definition_type": "6", "i": 8, "j": 0, "word": "pu", "definition": "pu"}]}