{"map_file": "map_1", "score": 8, "date": "20240624170504", "definitions": [{"definition_type": "3", "i": 0, "j": 0, "word": "componction", "definition": "componction"}, {"definition_type": "6", "i": 0, "j": 0, "word": "douanier", "definition": "douanier"}, {"definition_type": "3", "i": 0, "j": 6, "word": "brasier", "definition": "brasier"}, {"definition_type": "1", "i": 2, "j": 0, "word": "magenta", "definition": "magenta"}, {"definition_type": "2", "i": 3, "j": 5, "word": "moduler", "definition": "moduler"}, {"definition_type": "6", "i": 6, "j": 0, "word": "sternum", "definition": "sternum"}, {"definition_type": "1", "i": 8, "j": 0, "word": "insoler", "definition": "insoler"}, {"definition_type": "6", "i": 4, "j": 0, "word": "entomo", "definition": "entomo"}, {"definition_type": "2", "i": 4, "j": 3, "word": "oursin", "definition": "oursin"}, {"definition_type": "6", "i": 2, "j": 0, "word": "appat", "definition": "appat"}, {"definition_type": "2", "i": 5, "j": 6, "word": "emeri", "definition": "emeri"}, {"definition_type": "1", "i": 9, "j": 2, "word": "isere", "definition": "isere"}, {"definition_type": "3", "i": 0, "j": 2, "word": "saga", "definition": "saga"}, {"definition_type": "1", "i": 4, "j": 3, "word": "ambi", "definition": "ambi"}, {"definition_type": "3", "i": 0, "j": 4, "word": "vin", "definition": "vin"}, {"definition_type": "1", "i": 6, "j": 0, "word": "cru", "definition": "cru"}, {"definition_type": "1", "i": 6, "j": 4, "word": "der", "definition": "der"}, {"definition_type": "2", "i": 6, "j": 4, "word": "nos", "definition": "nos"}, {"definition_type": "2", "i": 7, "j": 7, "word": "res", "definition": "res"}, {"definition_type": "1", "i": 10, "j": 0, "word": "nan", "definition": "nan"}, {"definition_type": "1", "i": 10, "j": 4, "word": "ris", "definition": "ris"}, {"definition_type": "1", "i": 3, "j": 5, "word": "ps", "definition": "ps"}, {"definition_type": "1", "i": 4, "j": 0, "word": "ot", "definition": "ot"}, {"definition_type": "6", "i": 8, "j": 0, "word": "no", "definition": "no"}]}