{"map_file": "map_1", "score": 8, "date": "20240624170440", "definitions": [{"definition_type": "3", "i": 0, "j": 0, "word": "decuplement", "definition": "decuplement"}, {"definition_type": "6", "i": 0, "j": 0, "word": "peignoir", "definition": "peignoir"}, {"definition_type": "3", "i": 0, "j": 6, "word": "crottin", "definition": "crottin"}, {"definition_type": "1", "i": 2, "j": 0, "word": "cinzano", "definition": "cinzano"}, {"definition_type": "2", "i": 3, "j": 5, "word": "danette", "definition": "danette"}, {"definition_type": "6", "i": 6, "j": 0, "word": "emerger", "definition": "emerger"}, {"definition_type": "1", "i": 8, "j": 0, "word": "exalter", "definition": "exalter"}, {"definition_type": "6", "i": 4, "j": 0, "word": "plasma", "definition": "plasma"}, {"definition_type": "2", "i": 4, "j": 3, "word": "strato", "definition": "strato"}, {"definition_type": "6", "i": 2, "j": 0, "word": "juger", "definition": "juger"}, {"definition_type": "2", "i": 5, "j": 6, "word": "arete", "definition": "arete"}, {"definition_type": "1", "i": 9, "j": 2, "word": "tutti", "definition": "tutti"}, {"definition_type": "3", "i": 0, "j": 2, "word": "igne", "definition": "igne"}, {"definition_type": "1", "i": 4, "j": 3, "word": "edit", "definition": "edit"}, {"definition_type": "3", "i": 0, "j": 4, "word": "boa", "definition": "boa"}, {"definition_type": "1", "i": 6, "j": 0, "word": "est", "definition": "est"}, {"definition_type": "1", "i": 6, "j": 4, "word": "nan", "definition": "nan"}, {"definition_type": "2", "i": 6, "j": 4, "word": "glu", "definition": "glu"}, {"definition_type": "2", "i": 7, "j": 7, "word": "rin", "definition": "rin"}, {"definition_type": "1", "i": 10, "j": 0, "word": "tao", "definition": "tao"}, {"definition_type": "1", "i": 10, "j": 4, "word": "een", "definition": "een"}, {"definition_type": "1", "i": 3, "j": 5, "word": "ct", "definition": "ct"}, {"definition_type": "1", "i": 4, "j": 0, "word": "pd", "definition": "pd"}, {"definition_type": "6", "i": 8, "j": 0, "word": "en", "definition": "en"}]}